{
  "logins": [
    {
      "id": 1,
      "email": "def1@gmail.com",
      "password": "pass1"
    },
    {
      "id": 2,
      "email": "def2@gmail.com",
      "password": "pass2"
    },
    {
      "id": 3,
      "email": "def3@gmail.com",
      "password": "pass3"
    },
    {
      "id": 4,
      "email": "def4@gmail.com",
      "password": "pass4"
    },
    {
      "id": 5,
      "email": "def5@gmail.com",
      "password": "pass5"
    },
    {
      "id": 6,
      "email": "def6@gmail.com",
      "password": "pass6"
    },
    {
      "id": 7,
      "email": "def7@gmail.com",
      "password": "pass7"
    },
    {
      "id": 8,
      "email": "def8@gmail.com",
      "password": "pass8"
    },
    {
      "id": 9,
      "email": "def9@gmail.com",
      "password": "pass9"
    },
    {
      "id": 10,
      "email": "def10@gmail.com",
      "password": "pass10"
    },
    {
      "id": 11,
      "email": "def11@gmail.com",
      "password": "pass11"
    },
    {
      "id": 12,
      "email": "def12@gmail.com",
      "password": "pass12"
    },
    {
      "id": 13,
      "email": "def13@gmail.com",
      "password": "pass13"
    },
    {
      "id": 14,
      "email": "def14@gmail.com",
      "password": "pass14"
    },
    {
      "id": 15,
      "email": "def15@gmail.com",
      "password": "pass15"
    },
    {
      "id": 16,
      "email": "def16@gmail.com",
      "password": "pass16"
    },
    {
      "id": 17,
      "email": "def17@gmail.com",
      "password": "pass17"
    },
    {
      "id": 18,
      "email": "def18@gmail.com",
      "password": "pass18"
    }
  ],
  "users": [
    {
      "id": 1,
      "login": "rolandsvarsbergs",
      "first_name": "Rolands",
      "last_name": "Varsbergs",
      "bio": "Creator obsessed with landscapes.",
      "location": "Copenhagen",
      "profile_image": "https://images.unsplash.com/profile-fb-1552480754-7d470e6bfd8c.jpg?ixlib=rb-1.2.1&q=80&fm=jpg&crop=faces&cs=tinysrgb&fit=crop&h=128&w=128"
    },
    {
      "id": 2,
      "login": "theguywithacamera",
      "first_name": "Vincent",
      "last_name": "Riszdorfer",
      "bio": "Make sure to check out my Instagram for more.",
      "location": "Munich",
      "profile_image": "https://images.unsplash.com/profile-1541166970299-34e5d97cca5f?ixlib=rb-1.2.1&q=80&fm=jpg&crop=faces&cs=tinysrgb&fit=crop&h=128&w=128"
    },
    {
      "id": 3,
      "login": "jontyson",
      "first_name": "Jon",
      "last_name": "Tyson",
      "bio": "My cup overflows.",
      "location": "Hell's Kitchen New York",
      "profile_image": "https://images.unsplash.com/profile-1528230399047-c8d0d832ed9d?ixlib=rb-1.2.1&q=80&fm=jpg&crop=faces&cs=tinysrgb&fit=crop&h=128&w=128"
    },
    {
      "id": 4,
      "login": "bantersnaps",
      "first_name": "Banter",
      "last_name": "Snaps",
      "bio": "Edmonton Based Photographer",
      "location": "Edmonton, Alberta",
      "profile_image": "https://images.unsplash.com/profile-1539574891938-df9c355db618?ixlib=rb-1.2.1&q=80&fm=jpg&crop=faces&cs=tinysrgb&fit=crop&h=128&w=128"
    },
    {
      "id": 5,
      "login": "florenciaviadana",
      "first_name": "Florencia",
      "last_name": "Viadana",
      "bio": "I am a graphic designer based in Amsterdam. I run an independent design studio called Format Wars which specializes in Editorial design. Shooting is always a kind of therapy for me, like books, and silence. ",
      "location": "Amsterdam, Netherlands",
      "profile_image": "https://images.unsplash.com/profile-1552493977255-2ac9557f7853?ixlib=rb-1.2.1&q=80&fm=jpg&crop=faces&cs=tinysrgb&fit=crop&h=128&w=128"
    },
    {
      "id": 6,
      "login": "jakeallison",
      "first_name": "Jake",
      "last_name": "Allison",
      "bio": "Showcasing a different perspective of the worlds natural wonders...I use a Dji Mavic Pro and live in a small coastal town in Australia. If you enjoy my work, please support my Instagram (link above). Have a great day :)",
      "location": "Western Australia",
      "profile_image": "https://images.unsplash.com/profile-1551932233730-75d801969adb?ixlib=rb-1.2.1&q=80&fm=jpg&crop=faces&cs=tinysrgb&fit=crop&h=128&w=128"
    },
    {
      "id": 7,
      "login": "joshhild",
      "first_name": "Josh",
      "last_name": "Hild",
      "bio": "| joshhild.com | Taking freelance work, just message me.|",
      "location": "Minneapolis",
      "profile_image": "https://images.unsplash.com/profile-1534444770498-421ec361dce5?ixlib=rb-1.2.1&q=80&fm=jpg&crop=faces&cs=tinysrgb&fit=crop&h=128&w=128"
    },
    {
      "id": 8,
      "login": "katjahentschel",
      "first_name": "katja",
      "last_name": "hentschel",
      "bio": null,
      "location": null,
      "profile_image": "https://images.unsplash.com/profile-fb-1552353706-398a78f61592.jpg?ixlib=rb-1.2.1&q=80&fm=jpg&crop=faces&cs=tinysrgb&fit=crop&h=128&w=128"
    },
    {
      "id": 9,
      "login": "roadtojericho",
      "first_name": "Jericho",
      "last_name": "Cervantes",
      "bio": "Freelance photographer based in Rochester NY. Strong passion for landscape photography and the outdoors. Check out the print store on my website for fine art prints! ",
      "location": "Rochester NY",
      "profile_image": "https://images.unsplash.com/profile-1551485865634-81192965ae16?ixlib=rb-1.2.1&q=80&fm=jpg&crop=faces&cs=tinysrgb&fit=crop&h=128&w=128"
    },
    {
      "id": 10,
      "login": "taylorgsimpson",
      "first_name": "Taylor",
      "last_name": "Simpson",
      "bio": "Travel Photographer/ Instagram: @taylor.g.simpson",
      "location": "Palm Springs, CA",
      "profile_image": "https://images.unsplash.com/profile-1549155510462-b4926effe15c?ixlib=rb-1.2.1&q=80&fm=jpg&crop=faces&cs=tinysrgb&fit=crop&h=128&w=128"
    },
    {
      "id": 11,
      "login": "brittanyg",
      "first_name": "brittany",
      "last_name": "gaiser",
      "bio": "student who i guess likes taking photographs. currently posting like occasionally but you know probably petting my dog and trying to find something consistent",
      "location": "victoria. australia",
      "profile_image": "https://images.unsplash.com/profile-1547348439929-08a1ec5a148e?ixlib=rb-1.2.1&q=80&fm=jpg&crop=faces&cs=tinysrgb&fit=crop&h=128&w=128"
    },
    {
      "id": 12,
      "login": "markusspiske",
      "first_name": "Markus",
      "last_name": "Spiske",
      "bio": "||||||||||||||||| GRAPHICS. CODE. PHOTO. ||||||||||||||||||||||||||||||||||||||||||||||||||||||Authentic & everyday #unstock photos. Stunning lifestyle imagery for creatives. ||||||||||||||||| WWW.TEMPORAUSCH.COM |||||||||||||||||||||||",
      "location": "Erlangen/Forchheim, Bavaria, Germany",
      "profile_image": "https://images.unsplash.com/profile-1468003870880-1d44bae203c5?ixlib=rb-1.2.1&q=80&fm=jpg&crop=faces&cs=tinysrgb&fit=crop&h=128&w=128"
    },
    {
      "id": 13,
      "login": "siimlukka",
      "first_name": "Siim",
      "last_name": "Lukka",
      "bio": null,
      "location": null,
      "profile_image": "https://images.unsplash.com/profile-fb-1484647095-8eb898c682e7.jpg?ixlib=rb-1.2.1&q=80&fm=jpg&crop=faces&cs=tinysrgb&fit=crop&h=128&w=128"
    },
    {
      "id": 14,
      "login": "leeandstefania",
      "first_name": "Lee",
      "last_name": "Hnetinka",
      "bio": "Lee Hnetinka is the CEO and Founder of Darkstore, a delivery platform that provides different services to e-commerce brands.",
      "location": null,
      "profile_image": "https://images.unsplash.com/profile-1549435286547-332ec444bcb9?ixlib=rb-1.2.1&q=80&fm=jpg&crop=faces&cs=tinysrgb&fit=crop&h=128&w=128"
    },
    {
      "id": 15,
      "login": "seresigo",
      "first_name": "Philipp",
      "last_name": "Trubchenko",
      "bio": null,
      "location": "Moscow, Russia",
      "profile_image": "https://images.unsplash.com/profile-1552468388324-469cc701c5ca?ixlib=rb-1.2.1&q=80&fm=jpg&crop=faces&cs=tinysrgb&fit=crop&h=128&w=128"
    },
    {
      "id": 16,
      "login": "visualsoftheodor",
      "first_name": "Butunoi",
      "last_name": "Sergiu",
      "bio": "I hope you enjoy my photography. ",
      "location": null,
      "profile_image": "https://images.unsplash.com/profile-1552511205014-2b51f69002c9?ixlib=rb-1.2.1&q=80&fm=jpg&crop=faces&cs=tinysrgb&fit=crop&h=128&w=128"
    },
    {
      "id": 17,
      "login": "quadratmedia",
      "first_name": "Wolfgang",
      "last_name": "Rottmann",
      "bio": null,
      "location": "Germany",
      "profile_image": "https://images.unsplash.com/profile-fb-1552388815-189066d2a708.jpg?ixlib=rb-1.2.1&q=80&fm=jpg&crop=faces&cs=tinysrgb&fit=crop&h=128&w=128"
    },
    {
      "id": 18,
      "login": "moniqa",
      "first_name": "Monika",
      "last_name": "Grabkowska",
      "bio": "Food stylist & photographer. Loves nature and healthy food . Always happy to drink a good cup of coffee ☕️Girl from Poland living in Uk ",
      "location": "UK",
      "profile_image": "https://images.unsplash.com/profile-1500391272480-fa84aef91909?ixlib=rb-1.2.1&q=80&fm=jpg&crop=faces&cs=tinysrgb&fit=crop&h=128&w=128"
    }
  ],
  "photos": [
    {
      "id": 1,
      "userId": 1,
      "created_at": "2019-03-14T12:23:14-04:00",
      "description": "waterfall",
      "categories": [],
      "likes_count": 75,
      "liked_by": [
        "bantersnaps",
        "sanshi"
      ],
      "url": "https://images.unsplash.com/photo-1552580535-49f1f22dfbcb?ixlib=rb-1.2.1&q=80&fm=jpg&crop=entropy&cs=tinysrgb&w=1080&fit=max&ixid=eyJhcHBfaWQiOjYxMTUwfQ",
      "comments": [
        {
          "user": "rolandsvarsbergs",
          "text": "test from sasha",
          "date": "2019-03-18T16:54:11.212Z"
        },
        {
          "user": "bantersnaps",
          "text": "gcycgy",
          "date": "2019-03-18T22:44:40.261Z"
        }
      ]
    },
    {
      "id": 2,
      "userId": 2,
      "created_at": "2019-03-14T09:07:02-04:00",
      "description": null,
      "categories": [],
      "likes_count": 74,
      "liked_by": [],
      "url": "https://images.unsplash.com/photo-1552568675-248a988fe3a7?ixlib=rb-1.2.1&q=80&fm=jpg&crop=entropy&cs=tinysrgb&w=1080&fit=max&ixid=eyJhcHBfaWQiOjYxMTUwfQ",
      "comments": []
    },
    {
      "id": 3,
      "userId": 3,
      "created_at": "2019-03-14T20:18:10-04:00",
      "description": null,
      "categories": [],
      "likes_count": 86,
      "liked_by": [
        "rolandsvarsbergs",
        "sanshi"
      ],
      "url": "https://images.unsplash.com/photo-1552609034-5cc4969282a4?ixlib=rb-1.2.1&q=80&fm=jpg&crop=entropy&cs=tinysrgb&w=1080&fit=max&ixid=eyJhcHBfaWQiOjYxMTUwfQ",
      "comments": [
        {
          "user": "joshapplegate",
          "text": "test",
          "date": "2019-03-19T17:39:48.989Z"
        },
        {
          "user": "bantersnaps",
          "text": "zutru",
          "date": "2019-03-24T23:28:59.171Z"
        }
      ]
    },
    {
      "id": 4,
      "userId": 4,
      "created_at": "2019-03-15T00:13:45-04:00",
      "description": null,
      "categories": [],
      "likes_count": 43,
      "liked_by": [
        "theguywithacamera"
      ],
      "url": "https://images.unsplash.com/photo-1552623083-0bd5caaa07b1?ixlib=rb-1.2.1&q=80&fm=jpg&crop=entropy&cs=tinysrgb&w=1080&fit=max&ixid=eyJhcHBfaWQiOjYxMTUwfQ",
      "comments": []
    },
    {
      "id": 5,
      "userId": 5,
      "created_at": "2019-03-14T13:20:54-04:00",
      "description": null,
      "categories": [],
      "likes_count": 15,
      "liked_by": [
        "bantersnaps"
      ],
      "url": "https://images.unsplash.com/photo-1552583995-c307cfb8fe4a?ixlib=rb-1.2.1&q=80&fm=jpg&crop=entropy&cs=tinysrgb&w=1080&fit=max&ixid=eyJhcHBfaWQiOjYxMTUwfQ",
      "comments": []
    },
    {
      "id": 6,
      "userId": 6,
      "created_at": "2019-03-14T09:44:44-04:00",
      "description": null,
      "categories": [],
      "likes_count": "49",
      "liked_by": [],
      "url": "https://images.unsplash.com/photo-1552571021-c38625e5ab41?ixlib=rb-1.2.1&q=80&fm=jpg&crop=entropy&cs=tinysrgb&w=1080&fit=max&ixid=eyJhcHBfaWQiOjYxMTUwfQ",
      "comments": []
    },
    {
      "id": 7,
      "userId": 7,
      "created_at": "2019-03-14T09:30:10-04:00",
      "description": null,
      "categories": [],
      "likes_count": "62",
      "liked_by": [],
      "url": "https://images.unsplash.com/photo-1552570173-1e3d3eaf989c?ixlib=rb-1.2.1&q=80&fm=jpg&crop=entropy&cs=tinysrgb&w=1080&fit=max&ixid=eyJhcHBfaWQiOjYxMTUwfQ",
      "comments": []
    },
    {
      "id": 8,
      "userId": 4,
      "created_at": "2019-03-15T00:13:45-04:00",
      "description": null,
      "categories": [],
      "likes_count": 15,
      "liked_by": [],
      "url": "https://images.unsplash.com/photo-1552623083-e71f2a0821e8?ixlib=rb-1.2.1&q=80&fm=jpg&crop=entropy&cs=tinysrgb&w=1080&fit=max&ixid=eyJhcHBfaWQiOjYxMTUwfQ",
      "comments": []
    },
    {
      "id": 9,
      "userId": 8,
      "created_at": "2019-03-11T21:24:40-04:00",
      "description": null,
      "categories": [],
      "likes_count": 35,
      "liked_by": [
        "theguywithacamera"
      ],
      "url": "https://images.unsplash.com/photo-1552353854-b2d8adc44027?ixlib=rb-1.2.1&q=80&fm=jpg&crop=entropy&cs=tinysrgb&w=1080&fit=max&ixid=eyJhcHBfaWQiOjYxMTUwfQ",
      "comments": []
    },
    {
      "id": 10,
      "userId": 5,
      "created_at": "2019-03-14T13:20:54-04:00",
      "description": null,
      "categories": [],
      "likes_count": "21",
      "liked_by": [],
      "url": "https://images.unsplash.com/photo-1552584002-f34682a9c5a9?ixlib=rb-1.2.1&q=80&fm=jpg&crop=entropy&cs=tinysrgb&w=1080&fit=max&ixid=eyJhcHBfaWQiOjYxMTUwfQ",
      "comments": []
    },
    {
      "id": 11,
      "userId": 4,
      "created_at": "2019-03-15T00:32:50-04:00",
      "description": null,
      "categories": [],
      "likes_count": 24,
      "liked_by": [],
      "url": "https://images.unsplash.com/photo-1552624189-4d11de373049?ixlib=rb-1.2.1&q=80&fm=jpg&crop=entropy&cs=tinysrgb&w=1080&fit=max&ixid=eyJhcHBfaWQiOjYxMTUwfQ",
      "comments": []
    },
    {
      "id": 12,
      "userId": 9,
      "created_at": "2019-03-14T10:07:52-04:00",
      "description": null,
      "categories": [],
      "likes_count": "56",
      "liked_by": [],
      "url": "https://images.unsplash.com/photo-1552572455-1e855bd25a18?ixlib=rb-1.2.1&q=80&fm=jpg&crop=entropy&cs=tinysrgb&w=1080&fit=max&ixid=eyJhcHBfaWQiOjYxMTUwfQ",
      "comments": []
    },
    {
      "id": 13,
      "userId": 11,
      "created_at": "2019-03-14T20:23:21-04:00",
      "description": null,
      "categories": [],
      "likes_count": "24",
      "liked_by": [],
      "url": "https://images.unsplash.com/photo-1552608992-48f3f7d52205?ixlib=rb-1.2.1&q=80&fm=jpg&crop=entropy&cs=tinysrgb&w=1080&fit=max&ixid=eyJhcHBfaWQiOjYxMTUwfQ",
      "comments": []
    },
    {
      "id": 14,
      "userId": 4,
      "created_at": "2019-03-15T00:32:50-04:00",
      "description": null,
      "categories": [],
      "likes_count": "19",
      "liked_by": [],
      "url": "https://images.unsplash.com/photo-1552624189-cf10026a305b?ixlib=rb-1.2.1&q=80&fm=jpg&crop=entropy&cs=tinysrgb&w=1080&fit=max&ixid=eyJhcHBfaWQiOjYxMTUwfQ",
      "comments": []
    },
    {
      "id": 15,
      "userId": 13,
      "created_at": "2019-03-14T10:07:40-04:00",
      "description": null,
      "categories": [],
      "likes_count": 29,
      "liked_by": [
        "rolandsvarsbergs"
      ],
      "url": "https://images.unsplash.com/photo-1552572454-88d1b8011ca6?ixlib=rb-1.2.1&q=80&fm=jpg&crop=entropy&cs=tinysrgb&w=1080&fit=max&ixid=eyJhcHBfaWQiOjYxMTUwfQ",
      "comments": []
    },
    {
      "id": 16,
      "userId": 12,
      "created_at": "2019-03-15T01:29:02-04:00",
      "description": null,
      "categories": [],
      "likes_count": "17",
      "liked_by": [],
      "url": "https://images.unsplash.com/photo-1552627716-7d1faa4282f1?ixlib=rb-1.2.1&q=80&fm=jpg&crop=entropy&cs=tinysrgb&w=1080&fit=max&ixid=eyJhcHBfaWQiOjYxMTUwfQ",
      "comments": []
    },
    {
      "id": 17,
      "userId": 14,
      "created_at": "2019-03-14T00:51:19-04:00",
      "description": null,
      "categories": [],
      "likes_count": "11",
      "liked_by": [],
      "url": "https://images.unsplash.com/photo-1552539061-c90606121ab3?ixlib=rb-1.2.1&q=80&fm=jpg&crop=entropy&cs=tinysrgb&w=1080&fit=max&ixid=eyJhcHBfaWQiOjYxMTUwfQ",
      "comments": []
    },
    {
      "id": 18,
      "userId": 4,
      "created_at": "2019-03-15T00:32:50-04:00",
      "description": null,
      "categories": [],
      "likes_count": "22",
      "liked_by": [],
      "url": "https://images.unsplash.com/photo-1552624190-54dbd7f73993?ixlib=rb-1.2.1&q=80&fm=jpg&crop=entropy&cs=tinysrgb&w=1080&fit=max&ixid=eyJhcHBfaWQiOjYxMTUwfQ",
      "comments": []
    },
    {
      "id": 19,
      "userId": 10,
      "created_at": "2019-03-14T23:35:00-04:00",
      "description": null,
      "categories": [],
      "likes_count": 31,
      "liked_by": [],
      "url": "https://images.unsplash.com/photo-1552620888-a4553dd93b5e?ixlib=rb-1.2.1&q=80&fm=jpg&crop=entropy&cs=tinysrgb&w=1080&fit=max&ixid=eyJhcHBfaWQiOjYxMTUwfQ",
      "comments": []
    },
    {
      "id": 20,
      "userId": 17,
      "created_at": "2019-03-14T08:34:01-04:00",
      "description": null,
      "categories": [],
      "likes_count": "21",
      "liked_by": [],
      "url": "https://images.unsplash.com/photo-1552566827-281f334d6fd5?ixlib=rb-1.2.1&q=80&fm=jpg&crop=entropy&cs=tinysrgb&w=1080&fit=max&ixid=eyJhcHBfaWQiOjYxMTUwfQ",
      "comments": [
        {
          "user": "bantersnaps",
          "text": "khbkhbi",
          "date": "2019-03-23T08:10:45.198Z"
        },
        {
          "user": "bantersnaps",
          "text": "hfcyc\n\n",
          "date": "2019-03-23T08:10:46.373Z"
        }
      ]
    },
    {
      "id": 21,
      "userId": 18,
      "created_at": "2019-03-14T13:53:08-04:00",
      "description": null,
      "categories": [],
      "likes_count": "22",
      "liked_by": [],
      "url": "https://images.unsplash.com/photo-1552585960-0e1069ce7405?ixlib=rb-1.2.1&q=80&fm=jpg&crop=entropy&cs=tinysrgb&w=1080&fit=max&ixid=eyJhcHBfaWQiOjYxMTUwfQ",
      "comments": []
    },
    {
      "id": 22,
      "userId": 15,
      "created_at": "2019-03-14T14:33:06-04:00",
      "description": null,
      "categories": [],
      "likes_count": "53",
      "liked_by": [],
      "url": "https://images.unsplash.com/photo-1552588355-23e1b81409cd?ixlib=rb-1.2.1&q=80&fm=jpg&crop=entropy&cs=tinysrgb&w=1080&fit=max&ixid=eyJhcHBfaWQiOjYxMTUwfQ",
      "comments": []
    },
    {
      "id": 23,
      "userId": 16,
      "created_at": "2019-03-13T17:14:09-04:00",
      "description": null,
      "categories": [],
      "likes_count": 32,
      "liked_by": [
        "bantersnaps"
      ],
      "url": "https://images.unsplash.com/photo-1552511602-8058925f84ed?ixlib=rb-1.2.1&q=80&fm=jpg&crop=entropy&cs=tinysrgb&w=1080&fit=max&ixid=eyJhcHBfaWQiOjYxMTUwfQ",
      "comments": []
    },
    {
      "id": 24,
      "userId": 7,
      "created_at": "2019-03-14T09:30:10-04:00",
      "description": null,
      "categories": [],
      "likes_count": "42",
      "liked_by": [],
      "url": "https://images.unsplash.com/photo-1552570173-43e2d76c37f4?ixlib=rb-1.2.1&q=80&fm=jpg&crop=entropy&cs=tinysrgb&w=1080&fit=max&ixid=eyJhcHBfaWQiOjYxMTUwfQ",
      "comments": []
    }
  ]
}